[
    {
        "timestamp": "2026-05-10 22:49:55.764495",
        "action": "Blocked malicious activity",
        "threat": "[2026-05-10 22:44:39] ALERT: Privilege escalation detected"
    },
    {
        "timestamp": "2026-05-10 22:49:55.764771",
        "action": "Blocked malicious activity",
        "threat": "[2026-05-10 22:44:44] ALERT: Privilege escalation detected"
    },
    {
        "timestamp": "2026-05-10 22:49:55.765403",
        "action": "Blocked malicious activity",
        "threat": "[2026-05-10 22:44:59] ALERT: Potential brute force attack detected"
    },
    {
        "timestamp": "2026-05-10 22:49:55.765753",
        "action": "Blocked malicious activity",
        "threat": "[2026-05-10 22:45:09] ALERT: Privilege escalation detected"
    },
    {
        "timestamp": "2026-05-10 22:49:55.766253",
        "action": "Blocked malicious activity",
        "threat": "[2026-05-10 22:45:24] ALERT: Potential brute force attack detected"
    },
    {
        "timestamp": "2026-05-10 22:49:55.768196",
        "action": "Blocked malicious activity",
        "threat": "[2026-05-10 22:46:14] ALERT: Potential brute force attack detected"
    },
    {
        "timestamp": "2026-05-10 22:49:55.768375",
        "action": "Blocked malicious activity",
        "threat": "[2026-05-10 22:46:19] ALERT: Potential brute force attack detected"
    },
    {
        "timestamp": "2026-05-10 22:49:55.769217",
        "action": "Blocked malicious activity",
        "threat": "[2026-05-10 22:46:39] ALERT: Unauthorized admin access attempt"
    },
    {
        "timestamp": "2026-05-10 22:49:55.769534",
        "action": "Blocked malicious activity",
        "threat": "[2026-05-10 22:46:44] ALERT: Privilege escalation detected"
    },
    {
        "timestamp": "2026-05-10 22:49:55.772086",
        "action": "Blocked malicious activity",
        "threat": "[2026-05-10 22:47:24] ALERT: Potential brute force attack detected"
    },
    {
        "timestamp": "2026-05-10 22:49:55.772494",
        "action": "Blocked malicious activity",
        "threat": "[2026-05-10 22:47:29] ALERT: Privilege escalation detected"
    },
    {
        "timestamp": "2026-05-10 22:49:55.773240",
        "action": "Blocked malicious activity",
        "threat": "[2026-05-10 22:47:39] ALERT: Potential brute force attack detected"
    },
    {
        "timestamp": "2026-05-10 22:49:55.774226",
        "action": "Blocked malicious activity",
        "threat": "[2026-05-10 22:47:44] ALERT: Privilege escalation detected"
    },
    {
        "timestamp": "2026-05-10 22:49:55.774733",
        "action": "Blocked malicious activity",
        "threat": "[2026-05-10 22:47:49] ALERT: Potential brute force attack detected"
    },
    {
        "timestamp": "2026-05-10 22:53:20.026158",
        "action": "Blocked malicious activity",
        "threat": "[2026-05-10 22:53:19] ALERT: Potential brute force attack detected"
    },
    {
        "timestamp": "2026-05-10 22:53:23.499732",
        "action": "Blocked malicious activity",
        "threat": "[2026-05-10 22:44:39] ALERT: Privilege escalation detected"
    },
    {
        "timestamp": "2026-05-10 22:53:23.500536",
        "action": "Blocked malicious activity",
        "threat": "[2026-05-10 22:44:44] ALERT: Privilege escalation detected"
    },
    {
        "timestamp": "2026-05-10 22:53:23.502444",
        "action": "Blocked malicious activity",
        "threat": "[2026-05-10 22:44:59] ALERT: Potential brute force attack detected"
    },
    {
        "timestamp": "2026-05-10 22:53:23.503978",
        "action": "Blocked malicious activity",
        "threat": "[2026-05-10 22:45:09] ALERT: Privilege escalation detected"
    },
    {
        "timestamp": "2026-05-10 22:53:23.505447",
        "action": "Blocked malicious activity",
        "threat": "[2026-05-10 22:45:24] ALERT: Potential brute force attack detected"
    },
    {
        "timestamp": "2026-05-10 22:53:23.510734",
        "action": "Blocked malicious activity",
        "threat": "[2026-05-10 22:46:14] ALERT: Potential brute force attack detected"
    },
    {
        "timestamp": "2026-05-10 22:53:23.511153",
        "action": "Blocked malicious activity",
        "threat": "[2026-05-10 22:46:19] ALERT: Potential brute force attack detected"
    },
    {
        "timestamp": "2026-05-10 22:53:23.513543",
        "action": "Blocked malicious activity",
        "threat": "[2026-05-10 22:46:39] ALERT: Unauthorized admin access attempt"
    },
    {
        "timestamp": "2026-05-10 22:53:23.513899",
        "action": "Blocked malicious activity",
        "threat": "[2026-05-10 22:46:44] ALERT: Privilege escalation detected"
    },
    {
        "timestamp": "2026-05-10 22:53:23.517331",
        "action": "Blocked malicious activity",
        "threat": "[2026-05-10 22:47:24] ALERT: Potential brute force attack detected"
    },
    {
        "timestamp": "2026-05-10 22:53:23.517687",
        "action": "Blocked malicious activity",
        "threat": "[2026-05-10 22:47:29] ALERT: Privilege escalation detected"
    },
    {
        "timestamp": "2026-05-10 22:53:23.520360",
        "action": "Blocked malicious activity",
        "threat": "[2026-05-10 22:47:39] ALERT: Potential brute force attack detected"
    },
    {
        "timestamp": "2026-05-10 22:53:23.521745",
        "action": "Blocked malicious activity",
        "threat": "[2026-05-10 22:47:44] ALERT: Privilege escalation detected"
    },
    {
        "timestamp": "2026-05-10 22:53:23.522923",
        "action": "Blocked malicious activity",
        "threat": "[2026-05-10 22:47:49] ALERT: Potential brute force attack detected"
    },
    {
        "timestamp": "2026-05-10 22:53:23.526887",
        "action": "Blocked malicious activity",
        "threat": "[2026-05-10 22:53:19] ALERT: Potential brute force attack detected"
    },
    {
        "timestamp": "2026-05-10 22:53:32.539637",
        "action": "Blocked malicious activity",
        "threat": "[2026-05-10 22:53:29] ALERT: Potential brute force attack detected"
    },
    {
        "timestamp": "2026-05-10 22:53:35.546969",
        "action": "Blocked malicious activity",
        "threat": "[2026-05-10 22:53:34] ALERT: Privilege escalation detected"
    },
    {
        "timestamp": "2026-05-10 22:53:50.576315",
        "action": "Blocked malicious activity",
        "threat": "[2026-05-10 22:53:50] ALERT: Privilege escalation detected"
    },
    {
        "timestamp": "2026-05-10 22:54:02.594258",
        "action": "Blocked malicious activity",
        "threat": "[2026-05-10 22:54:00] ALERT: Privilege escalation detected"
    },
    {
        "timestamp": "2026-05-10 22:54:05.596121",
        "action": "Blocked malicious activity",
        "threat": "[2026-05-10 22:54:05] ALERT: Privilege escalation detected"
    },
    {
        "timestamp": "2026-05-10 22:54:11.603140",
        "action": "Blocked malicious activity",
        "threat": "[2026-05-10 22:54:10] ALERT: Potential brute force attack detected"
    },
    {
        "timestamp": "2026-05-10 22:54:50.671974",
        "action": "Blocked malicious activity",
        "threat": "[2026-05-10 22:54:50] ALERT: Unauthorized admin access attempt"
    },
    {
        "timestamp": "2026-05-10 22:54:56.686074",
        "action": "Blocked malicious activity",
        "threat": "[2026-05-10 22:54:55] ALERT: Potential brute force attack detected"
    },
    {
        "timestamp": "2026-05-10 22:55:02.697815",
        "action": "Blocked malicious activity",
        "threat": "[2026-05-10 22:55:00] ALERT: Privilege escalation detected"
    },
    {
        "timestamp": "2026-05-10 22:55:11.717179",
        "action": "Blocked malicious activity",
        "threat": "[2026-05-10 22:55:10] ALERT: Potential brute force attack detected"
    },
    {
        "timestamp": "2026-05-10 22:55:17.728811",
        "action": "Blocked malicious activity",
        "threat": "[2026-05-10 22:55:15] ALERT: Potential brute force attack detected"
    },
    {
        "timestamp": "2026-05-10 22:55:20.735930",
        "action": "Blocked malicious activity",
        "threat": "[2026-05-10 22:55:20] ALERT: Privilege escalation detected"
    },
    {
        "timestamp": "2026-05-10 22:55:50.788402",
        "action": "Blocked malicious activity",
        "threat": "[2026-05-10 22:55:50] ALERT: Unauthorized admin access attempt"
    },
    {
        "timestamp": "2026-05-10 22:55:56.798504",
        "action": "Blocked malicious activity",
        "threat": "[2026-05-10 22:55:55] ALERT: Privilege escalation detected"
    },
    {
        "timestamp": "2026-05-10 22:56:11.821383",
        "action": "Blocked malicious activity",
        "threat": "[2026-05-10 22:56:10] ALERT: Unauthorized admin access attempt"
    },
    {
        "timestamp": "2026-05-10 22:56:17.829278",
        "action": "Blocked malicious activity",
        "threat": "[2026-05-10 22:56:15] ALERT: Privilege escalation detected"
    },
    {
        "timestamp": "2026-05-10 22:56:20.836480",
        "action": "Blocked malicious activity",
        "threat": "[2026-05-10 22:56:20] ALERT: Unauthorized admin access attempt"
    },
    {
        "timestamp": "2026-05-10 22:56:32.858147",
        "action": "Blocked malicious activity",
        "threat": "[2026-05-10 22:56:30] ALERT: Privilege escalation detected"
    },
    {
        "timestamp": "2026-05-10 22:56:56.894943",
        "action": "Blocked malicious activity",
        "threat": "[2026-05-10 22:56:55] ALERT: Privilege escalation detected"
    },
    {
        "timestamp": "2026-05-10 22:57:02.902710",
        "action": "Blocked malicious activity",
        "threat": "[2026-05-10 22:57:00] ALERT: Privilege escalation detected"
    },
    {
        "timestamp": "2026-05-10 22:57:17.924983",
        "action": "Blocked malicious activity",
        "threat": "[2026-05-10 22:57:15] ALERT: Privilege escalation detected"
    },
    {
        "timestamp": "2026-05-10 22:57:26.941275",
        "action": "Blocked malicious activity",
        "threat": "[2026-05-10 22:57:25] ALERT: Potential brute force attack detected"
    },
    {
        "timestamp": "2026-05-10 22:57:32.951860",
        "action": "Blocked malicious activity",
        "threat": "[2026-05-10 22:57:30] ALERT: Privilege escalation detected"
    },
    {
        "timestamp": "2026-05-10 22:57:41.969677",
        "action": "Blocked malicious activity",
        "threat": "[2026-05-10 22:57:40] ALERT: Unauthorized admin access attempt"
    },
    {
        "timestamp": "2026-05-10 22:57:47.981990",
        "action": "Blocked malicious activity",
        "threat": "[2026-05-10 22:57:45] ALERT: Potential brute force attack detected"
    },
    {
        "timestamp": "2026-05-10 22:57:56.996588",
        "action": "Blocked malicious activity",
        "threat": "[2026-05-10 22:57:55] ALERT: Unauthorized admin access attempt"
    },
    {
        "timestamp": "2026-05-10 22:58:03.002836",
        "action": "Blocked malicious activity",
        "threat": "[2026-05-10 22:58:00] ALERT: Unauthorized admin access attempt"
    },
    {
        "timestamp": "2026-05-10 22:58:12.013620",
        "action": "Blocked malicious activity",
        "threat": "[2026-05-10 22:58:10] ALERT: Unauthorized admin access attempt"
    },
    {
        "timestamp": "2026-05-10 22:58:21.031743",
        "action": "Blocked malicious activity",
        "threat": "[2026-05-10 22:58:20] ALERT: Potential brute force attack detected"
    },
    {
        "timestamp": "2026-05-10 22:58:27.042272",
        "action": "Blocked malicious activity",
        "threat": "[2026-05-10 22:58:25] ALERT: Potential brute force attack detected"
    },
    {
        "timestamp": "2026-05-10 22:58:33.051192",
        "action": "Blocked malicious activity",
        "threat": "[2026-05-10 22:58:30] ALERT: Potential brute force attack detected"
    },
    {
        "timestamp": "2026-05-10 22:58:36.059919",
        "action": "Blocked malicious activity",
        "threat": "[2026-05-10 22:58:35] ALERT: Unauthorized admin access attempt"
    },
    {
        "timestamp": "2026-05-10 22:58:57.105437",
        "action": "Blocked malicious activity",
        "threat": "[2026-05-10 22:58:55] ALERT: Unauthorized admin access attempt"
    },
    {
        "timestamp": "2026-05-10 22:59:12.141499",
        "action": "Blocked malicious activity",
        "threat": "[2026-05-10 22:59:10] ALERT: Potential brute force attack detected"
    },
    {
        "timestamp": "2026-05-10 22:59:21.155271",
        "action": "Blocked malicious activity",
        "threat": "[2026-05-10 22:59:20] ALERT: Potential brute force attack detected"
    },
    {
        "timestamp": "2026-05-10 22:59:36.182294",
        "action": "Blocked malicious activity",
        "threat": "[2026-05-10 22:59:35] ALERT: Potential brute force attack detected"
    },
    {
        "timestamp": "2026-05-10 22:59:57.225823",
        "action": "Blocked malicious activity",
        "threat": "[2026-05-10 22:59:55] ALERT: Privilege escalation detected"
    },
    {
        "timestamp": "2026-05-10 23:00:18.258921",
        "action": "Blocked malicious activity",
        "threat": "[2026-05-10 23:00:15] ALERT: Privilege escalation detected"
    },
    {
        "timestamp": "2026-05-10 23:00:21.268202",
        "action": "Blocked malicious activity",
        "threat": "[2026-05-10 23:00:20] ALERT: Potential brute force attack detected"
    },
    {
        "timestamp": "2026-05-10 23:00:42.324661",
        "action": "Blocked malicious activity",
        "threat": "[2026-05-10 23:00:40] ALERT: Potential brute force attack detected"
    },
    {
        "timestamp": "2026-05-10 23:01:06.409381",
        "action": "Blocked malicious activity",
        "threat": "[2026-05-10 23:01:05] ALERT: Potential brute force attack detected"
    },
    {
        "timestamp": "2026-05-10 23:01:15.430150",
        "action": "Blocked malicious activity",
        "threat": "[2026-05-10 23:01:15] ALERT: Privilege escalation detected"
    },
    {
        "timestamp": "2026-05-10 23:01:30.449118",
        "action": "Blocked malicious activity",
        "threat": "[2026-05-10 23:01:30] ALERT: Privilege escalation detected"
    },
    {
        "timestamp": "2026-05-10 23:01:45.479250",
        "action": "Blocked malicious activity",
        "threat": "[2026-05-10 23:01:45] ALERT: Privilege escalation detected"
    },
    {
        "timestamp": "2026-05-10 23:01:51.484329",
        "action": "Blocked malicious activity",
        "threat": "[2026-05-10 23:01:50] ALERT: Potential brute force attack detected"
    },
    {
        "timestamp": "2026-05-10 23:01:57.496708",
        "action": "Blocked malicious activity",
        "threat": "[2026-05-10 23:01:55] ALERT: Potential brute force attack detected"
    },
    {
        "timestamp": "2026-05-10 23:02:00.501230",
        "action": "Blocked malicious activity",
        "threat": "[2026-05-10 23:02:00] ALERT: Potential brute force attack detected"
    },
    {
        "timestamp": "2026-05-10 23:02:15.533358",
        "action": "Blocked malicious activity",
        "threat": "[2026-05-10 23:02:15] ALERT: Privilege escalation detected"
    },
    {
        "timestamp": "2026-05-10 23:02:36.568381",
        "action": "Blocked malicious activity",
        "threat": "[2026-05-10 23:02:35] ALERT: Privilege escalation detected"
    },
    {
        "timestamp": "2026-05-10 23:02:45.581468",
        "action": "Blocked malicious activity",
        "threat": "[2026-05-10 23:02:45] ALERT: Privilege escalation detected"
    },
    {
        "timestamp": "2026-05-10 23:03:06.619613",
        "action": "Blocked malicious activity",
        "threat": "[2026-05-10 23:03:05] ALERT: Potential brute force attack detected"
    },
    {
        "timestamp": "2026-05-10 23:03:15.642316",
        "action": "Blocked malicious activity",
        "threat": "[2026-05-10 23:03:15] ALERT: Unauthorized admin access attempt"
    },
    {
        "timestamp": "2026-05-10 23:03:27.663660",
        "action": "Blocked malicious activity",
        "threat": "[2026-05-10 23:03:25] ALERT: Unauthorized admin access attempt"
    },
    {
        "timestamp": "2026-05-10 23:04:00.729616",
        "action": "Blocked malicious activity",
        "threat": "[2026-05-10 23:04:00] ALERT: Privilege escalation detected"
    },
    {
        "timestamp": "2026-05-10 22:49:55.764495",
        "action": "Blocked malicious IP",
        "ip": "192.168.1.203",
        "threat": "[2026-05-10 22:44:39] ALERT: Privilege escalation detected"
    },
    {
        "timestamp": "2026-05-10 22:49:55.764771",
        "action": "Blocked malicious IP",
        "ip": "192.168.1.47",
        "threat": "[2026-05-10 22:44:44] ALERT: Privilege escalation detected"
    },
    {
        "timestamp": "2026-05-10 22:49:55.765403",
        "action": "Blocked malicious IP",
        "ip": "192.168.1.241",
        "threat": "[2026-05-10 22:44:59] ALERT: Potential brute force attack detected"
    },
    {
        "timestamp": "2026-05-10 22:49:55.765753",
        "action": "Blocked malicious IP",
        "ip": "192.168.1.238",
        "threat": "[2026-05-10 22:45:09] ALERT: Privilege escalation detected"
    },
    {
        "timestamp": "2026-05-10 22:49:55.766253",
        "action": "Blocked malicious IP",
        "ip": "192.168.1.210",
        "threat": "[2026-05-10 22:45:24] ALERT: Potential brute force attack detected"
    },
    {
        "timestamp": "2026-05-10 22:49:55.768196",
        "action": "Blocked malicious IP",
        "ip": "192.168.1.192",
        "threat": "[2026-05-10 22:46:14] ALERT: Potential brute force attack detected"
    },
    {
        "timestamp": "2026-05-10 22:49:55.768375",
        "action": "Blocked malicious IP",
        "ip": "192.168.1.11",
        "threat": "[2026-05-10 22:46:19] ALERT: Potential brute force attack detected"
    },
    {
        "timestamp": "2026-05-10 22:49:55.769217",
        "action": "Blocked malicious IP",
        "ip": "192.168.1.48",
        "threat": "[2026-05-10 22:46:39] ALERT: Unauthorized admin access attempt"
    },
    {
        "timestamp": "2026-05-10 22:49:55.769534",
        "action": "Blocked malicious IP",
        "ip": "192.168.1.170",
        "threat": "[2026-05-10 22:46:44] ALERT: Privilege escalation detected"
    },
    {
        "timestamp": "2026-05-10 22:49:55.772086",
        "action": "Blocked malicious IP",
        "ip": "192.168.1.248",
        "threat": "[2026-05-10 22:47:24] ALERT: Potential brute force attack detected"
    },
    {
        "timestamp": "2026-05-10 22:49:55.772494",
        "action": "Blocked malicious IP",
        "ip": "192.168.1.55",
        "threat": "[2026-05-10 22:47:29] ALERT: Privilege escalation detected"
    },
    {
        "timestamp": "2026-05-10 22:49:55.773240",
        "action": "Blocked malicious IP",
        "ip": "192.168.1.209",
        "threat": "[2026-05-10 22:47:39] ALERT: Potential brute force attack detected"
    },
    {
        "timestamp": "2026-05-10 22:49:55.774226",
        "action": "Blocked malicious IP",
        "ip": "192.168.1.226",
        "threat": "[2026-05-10 22:47:44] ALERT: Privilege escalation detected"
    },
    {
        "timestamp": "2026-05-10 22:49:55.774733",
        "action": "Blocked malicious IP",
        "ip": "192.168.1.211",
        "threat": "[2026-05-10 22:47:49] ALERT: Potential brute force attack detected"
    },
    {
        "timestamp": "2026-05-10 22:53:20.026158",
        "action": "Blocked malicious IP",
        "ip": "192.168.1.60",
        "threat": "[2026-05-10 22:53:19] ALERT: Potential brute force attack detected"
    },
    {
        "timestamp": "2026-05-10 22:53:23.499732",
        "action": "Blocked malicious IP",
        "ip": "192.168.1.144",
        "threat": "[2026-05-10 22:44:39] ALERT: Privilege escalation detected"
    },
    {
        "timestamp": "2026-05-10 22:53:23.500536",
        "action": "Blocked malicious IP",
        "ip": "192.168.1.24",
        "threat": "[2026-05-10 22:44:44] ALERT: Privilege escalation detected"
    },
    {
        "timestamp": "2026-05-10 22:53:23.502444",
        "action": "Blocked malicious IP",
        "ip": "192.168.1.23",
        "threat": "[2026-05-10 22:44:59] ALERT: Potential brute force attack detected"
    },
    {
        "timestamp": "2026-05-10 22:53:23.503978",
        "action": "Blocked malicious IP",
        "ip": "192.168.1.97",
        "threat": "[2026-05-10 22:45:09] ALERT: Privilege escalation detected"
    },
    {
        "timestamp": "2026-05-10 22:53:23.505447",
        "action": "Blocked malicious IP",
        "ip": "192.168.1.142",
        "threat": "[2026-05-10 22:45:24] ALERT: Potential brute force attack detected"
    },
    {
        "timestamp": "2026-05-10 22:53:23.510734",
        "action": "Blocked malicious IP",
        "ip": "192.168.1.253",
        "threat": "[2026-05-10 22:46:14] ALERT: Potential brute force attack detected"
    },
    {
        "timestamp": "2026-05-10 22:53:23.511153",
        "action": "Blocked malicious IP",
        "ip": "192.168.1.172",
        "threat": "[2026-05-10 22:46:19] ALERT: Potential brute force attack detected"
    },
    {
        "timestamp": "2026-05-10 22:53:23.513543",
        "action": "Blocked malicious IP",
        "ip": "192.168.1.188",
        "threat": "[2026-05-10 22:46:39] ALERT: Unauthorized admin access attempt"
    },
    {
        "timestamp": "2026-05-10 22:53:23.513899",
        "action": "Blocked malicious IP",
        "ip": "192.168.1.120",
        "threat": "[2026-05-10 22:46:44] ALERT: Privilege escalation detected"
    },
    {
        "timestamp": "2026-05-10 22:53:23.517331",
        "action": "Blocked malicious IP",
        "ip": "192.168.1.152",
        "threat": "[2026-05-10 22:47:24] ALERT: Potential brute force attack detected"
    },
    {
        "timestamp": "2026-05-10 22:53:23.517687",
        "action": "Blocked malicious IP",
        "ip": "192.168.1.201",
        "threat": "[2026-05-10 22:47:29] ALERT: Privilege escalation detected"
    },
    {
        "timestamp": "2026-05-10 22:53:23.520360",
        "action": "Blocked malicious IP",
        "ip": "192.168.1.184",
        "threat": "[2026-05-10 22:47:39] ALERT: Potential brute force attack detected"
    },
    {
        "timestamp": "2026-05-10 22:53:23.521745",
        "action": "Blocked malicious IP",
        "ip": "192.168.1.206",
        "threat": "[2026-05-10 22:47:44] ALERT: Privilege escalation detected"
    },
    {
        "timestamp": "2026-05-10 22:53:23.522923",
        "action": "Blocked malicious IP",
        "ip": "192.168.1.243",
        "threat": "[2026-05-10 22:47:49] ALERT: Potential brute force attack detected"
    },
    {
        "timestamp": "2026-05-10 22:53:23.526887",
        "action": "Blocked malicious IP",
        "ip": "192.168.1.106",
        "threat": "[2026-05-10 22:53:19] ALERT: Potential brute force attack detected"
    },
    {
        "timestamp": "2026-05-10 22:53:32.539637",
        "action": "Blocked malicious IP",
        "ip": "192.168.1.164",
        "threat": "[2026-05-10 22:53:29] ALERT: Potential brute force attack detected"
    },
    {
        "timestamp": "2026-05-10 22:53:35.546969",
        "action": "Blocked malicious IP",
        "ip": "192.168.1.207",
        "threat": "[2026-05-10 22:53:34] ALERT: Privilege escalation detected"
    },
    {
        "timestamp": "2026-05-10 22:53:50.576315",
        "action": "Blocked malicious IP",
        "ip": "192.168.1.25",
        "threat": "[2026-05-10 22:53:50] ALERT: Privilege escalation detected"
    },
    {
        "timestamp": "2026-05-10 22:54:02.594258",
        "action": "Blocked malicious IP",
        "ip": "192.168.1.234",
        "threat": "[2026-05-10 22:54:00] ALERT: Privilege escalation detected"
    },
    {
        "timestamp": "2026-05-10 22:54:05.596121",
        "action": "Blocked malicious IP",
        "ip": "192.168.1.167",
        "threat": "[2026-05-10 22:54:05] ALERT: Privilege escalation detected"
    },
    {
        "timestamp": "2026-05-10 22:54:11.603140",
        "action": "Blocked malicious IP",
        "ip": "192.168.1.179",
        "threat": "[2026-05-10 22:54:10] ALERT: Potential brute force attack detected"
    },
    {
        "timestamp": "2026-05-10 22:54:50.671974",
        "action": "Blocked malicious IP",
        "ip": "192.168.1.95",
        "threat": "[2026-05-10 22:54:50] ALERT: Unauthorized admin access attempt"
    },
    {
        "timestamp": "2026-05-10 22:54:56.686074",
        "action": "Blocked malicious IP",
        "ip": "192.168.1.166",
        "threat": "[2026-05-10 22:54:55] ALERT: Potential brute force attack detected"
    },
    {
        "timestamp": "2026-05-10 22:55:02.697815",
        "action": "Blocked malicious IP",
        "ip": "192.168.1.207",
        "threat": "[2026-05-10 22:55:00] ALERT: Privilege escalation detected"
    },
    {
        "timestamp": "2026-05-10 22:55:11.717179",
        "action": "Blocked malicious IP",
        "ip": "192.168.1.189",
        "threat": "[2026-05-10 22:55:10] ALERT: Potential brute force attack detected"
    },
    {
        "timestamp": "2026-05-10 22:55:17.728811",
        "action": "Blocked malicious IP",
        "ip": "192.168.1.253",
        "threat": "[2026-05-10 22:55:15] ALERT: Potential brute force attack detected"
    },
    {
        "timestamp": "2026-05-10 22:55:20.735930",
        "action": "Blocked malicious IP",
        "ip": "192.168.1.164",
        "threat": "[2026-05-10 22:55:20] ALERT: Privilege escalation detected"
    },
    {
        "timestamp": "2026-05-10 22:55:50.788402",
        "action": "Blocked malicious IP",
        "ip": "192.168.1.60",
        "threat": "[2026-05-10 22:55:50] ALERT: Unauthorized admin access attempt"
    },
    {
        "timestamp": "2026-05-10 22:55:56.798504",
        "action": "Blocked malicious IP",
        "ip": "192.168.1.9",
        "threat": "[2026-05-10 22:55:55] ALERT: Privilege escalation detected"
    },
    {
        "timestamp": "2026-05-10 22:56:11.821383",
        "action": "Blocked malicious IP",
        "ip": "192.168.1.174",
        "threat": "[2026-05-10 22:56:10] ALERT: Unauthorized admin access attempt"
    },
    {
        "timestamp": "2026-05-10 22:56:17.829278",
        "action": "Blocked malicious IP",
        "ip": "192.168.1.122",
        "threat": "[2026-05-10 22:56:15] ALERT: Privilege escalation detected"
    },
    {
        "timestamp": "2026-05-10 22:56:20.836480",
        "action": "Blocked malicious IP",
        "ip": "192.168.1.49",
        "threat": "[2026-05-10 22:56:20] ALERT: Unauthorized admin access attempt"
    },
    {
        "timestamp": "2026-05-10 22:56:32.858147",
        "action": "Blocked malicious IP",
        "ip": "192.168.1.180",
        "threat": "[2026-05-10 22:56:30] ALERT: Privilege escalation detected"
    },
    {
        "timestamp": "2026-05-10 22:56:56.894943",
        "action": "Blocked malicious IP",
        "ip": "192.168.1.216",
        "threat": "[2026-05-10 22:56:55] ALERT: Privilege escalation detected"
    },
    {
        "timestamp": "2026-05-10 22:57:02.902710",
        "action": "Blocked malicious IP",
        "ip": "192.168.1.254",
        "threat": "[2026-05-10 22:57:00] ALERT: Privilege escalation detected"
    },
    {
        "timestamp": "2026-05-10 22:57:17.924983",
        "action": "Blocked malicious IP",
        "ip": "192.168.1.9",
        "threat": "[2026-05-10 22:57:15] ALERT: Privilege escalation detected"
    },
    {
        "timestamp": "2026-05-10 22:57:26.941275",
        "action": "Blocked malicious IP",
        "ip": "192.168.1.136",
        "threat": "[2026-05-10 22:57:25] ALERT: Potential brute force attack detected"
    },
    {
        "timestamp": "2026-05-10 22:57:32.951860",
        "action": "Blocked malicious IP",
        "ip": "192.168.1.142",
        "threat": "[2026-05-10 22:57:30] ALERT: Privilege escalation detected"
    },
    {
        "timestamp": "2026-05-10 22:57:41.969677",
        "action": "Blocked malicious IP",
        "ip": "192.168.1.109",
        "threat": "[2026-05-10 22:57:40] ALERT: Unauthorized admin access attempt"
    },
    {
        "timestamp": "2026-05-10 22:57:47.981990",
        "action": "Blocked malicious IP",
        "ip": "192.168.1.192",
        "threat": "[2026-05-10 22:57:45] ALERT: Potential brute force attack detected"
    },
    {
        "timestamp": "2026-05-10 22:57:56.996588",
        "action": "Blocked malicious IP",
        "ip": "192.168.1.135",
        "threat": "[2026-05-10 22:57:55] ALERT: Unauthorized admin access attempt"
    },
    {
        "timestamp": "2026-05-10 22:58:03.002836",
        "action": "Blocked malicious IP",
        "ip": "192.168.1.132",
        "threat": "[2026-05-10 22:58:00] ALERT: Unauthorized admin access attempt"
    },
    {
        "timestamp": "2026-05-10 22:58:12.013620",
        "action": "Blocked malicious IP",
        "ip": "192.168.1.222",
        "threat": "[2026-05-10 22:58:10] ALERT: Unauthorized admin access attempt"
    },
    {
        "timestamp": "2026-05-10 22:58:21.031743",
        "action": "Blocked malicious IP",
        "ip": "192.168.1.217",
        "threat": "[2026-05-10 22:58:20] ALERT: Potential brute force attack detected"
    },
    {
        "timestamp": "2026-05-10 22:58:27.042272",
        "action": "Blocked malicious IP",
        "ip": "192.168.1.31",
        "threat": "[2026-05-10 22:58:25] ALERT: Potential brute force attack detected"
    },
    {
        "timestamp": "2026-05-10 22:58:33.051192",
        "action": "Blocked malicious IP",
        "ip": "192.168.1.130",
        "threat": "[2026-05-10 22:58:30] ALERT: Potential brute force attack detected"
    },
    {
        "timestamp": "2026-05-10 22:58:36.059919",
        "action": "Blocked malicious IP",
        "ip": "192.168.1.137",
        "threat": "[2026-05-10 22:58:35] ALERT: Unauthorized admin access attempt"
    },
    {
        "timestamp": "2026-05-10 22:58:57.105437",
        "action": "Blocked malicious IP",
        "ip": "192.168.1.21",
        "threat": "[2026-05-10 22:58:55] ALERT: Unauthorized admin access attempt"
    },
    {
        "timestamp": "2026-05-10 22:59:12.141499",
        "action": "Blocked malicious IP",
        "ip": "192.168.1.55",
        "threat": "[2026-05-10 22:59:10] ALERT: Potential brute force attack detected"
    },
    {
        "timestamp": "2026-05-10 22:59:21.155271",
        "action": "Blocked malicious IP",
        "ip": "192.168.1.202",
        "threat": "[2026-05-10 22:59:20] ALERT: Potential brute force attack detected"
    },
    {
        "timestamp": "2026-05-10 22:59:36.182294",
        "action": "Blocked malicious IP",
        "ip": "192.168.1.121",
        "threat": "[2026-05-10 22:59:35] ALERT: Potential brute force attack detected"
    },
    {
        "timestamp": "2026-05-10 22:59:57.225823",
        "action": "Blocked malicious IP",
        "ip": "192.168.1.115",
        "threat": "[2026-05-10 22:59:55] ALERT: Privilege escalation detected"
    },
    {
        "timestamp": "2026-05-10 23:00:18.258921",
        "action": "Blocked malicious IP",
        "ip": "192.168.1.253",
        "threat": "[2026-05-10 23:00:15] ALERT: Privilege escalation detected"
    },
    {
        "timestamp": "2026-05-10 23:00:21.268202",
        "action": "Blocked malicious IP",
        "ip": "192.168.1.113",
        "threat": "[2026-05-10 23:00:20] ALERT: Potential brute force attack detected"
    },
    {
        "timestamp": "2026-05-10 23:00:42.324661",
        "action": "Blocked malicious IP",
        "ip": "192.168.1.252",
        "threat": "[2026-05-10 23:00:40] ALERT: Potential brute force attack detected"
    },
    {
        "timestamp": "2026-05-10 23:01:06.409381",
        "action": "Blocked malicious IP",
        "ip": "192.168.1.173",
        "threat": "[2026-05-10 23:01:05] ALERT: Potential brute force attack detected"
    },
    {
        "timestamp": "2026-05-10 23:01:15.430150",
        "action": "Blocked malicious IP",
        "ip": "192.168.1.157",
        "threat": "[2026-05-10 23:01:15] ALERT: Privilege escalation detected"
    },
    {
        "timestamp": "2026-05-10 23:01:30.449118",
        "action": "Blocked malicious IP",
        "ip": "192.168.1.160",
        "threat": "[2026-05-10 23:01:30] ALERT: Privilege escalation detected"
    },
    {
        "timestamp": "2026-05-10 23:01:45.479250",
        "action": "Blocked malicious IP",
        "ip": "192.168.1.8",
        "threat": "[2026-05-10 23:01:45] ALERT: Privilege escalation detected"
    },
    {
        "timestamp": "2026-05-10 23:01:51.484329",
        "action": "Blocked malicious IP",
        "ip": "192.168.1.48",
        "threat": "[2026-05-10 23:01:50] ALERT: Potential brute force attack detected"
    },
    {
        "timestamp": "2026-05-10 23:01:57.496708",
        "action": "Blocked malicious IP",
        "ip": "192.168.1.212",
        "threat": "[2026-05-10 23:01:55] ALERT: Potential brute force attack detected"
    },
    {
        "timestamp": "2026-05-10 23:02:00.501230",
        "action": "Blocked malicious IP",
        "ip": "192.168.1.190",
        "threat": "[2026-05-10 23:02:00] ALERT: Potential brute force attack detected"
    },
    {
        "timestamp": "2026-05-10 23:02:15.533358",
        "action": "Blocked malicious IP",
        "ip": "192.168.1.167",
        "threat": "[2026-05-10 23:02:15] ALERT: Privilege escalation detected"
    },
    {
        "timestamp": "2026-05-10 23:02:36.568381",
        "action": "Blocked malicious IP",
        "ip": "192.168.1.192",
        "threat": "[2026-05-10 23:02:35] ALERT: Privilege escalation detected"
    },
    {
        "timestamp": "2026-05-10 23:02:45.581468",
        "action": "Blocked malicious IP",
        "ip": "192.168.1.242",
        "threat": "[2026-05-10 23:02:45] ALERT: Privilege escalation detected"
    },
    {
        "timestamp": "2026-05-10 23:03:06.619613",
        "action": "Blocked malicious IP",
        "ip": "192.168.1.123",
        "threat": "[2026-05-10 23:03:05] ALERT: Potential brute force attack detected"
    },
    {
        "timestamp": "2026-05-10 23:03:15.642316",
        "action": "Blocked malicious IP",
        "ip": "192.168.1.2",
        "threat": "[2026-05-10 23:03:15] ALERT: Unauthorized admin access attempt"
    },
    {
        "timestamp": "2026-05-10 23:03:27.663660",
        "action": "Blocked malicious IP",
        "ip": "192.168.1.216",
        "threat": "[2026-05-10 23:03:25] ALERT: Unauthorized admin access attempt"
    },
    {
        "timestamp": "2026-05-10 23:04:00.729616",
        "action": "Blocked malicious IP",
        "ip": "192.168.1.83",
        "threat": "[2026-05-10 23:04:00] ALERT: Privilege escalation detected"
    },
    {
        "timestamp": "2026-05-10 23:04:12.747706",
        "action": "Blocked malicious activity",
        "threat": "[2026-05-10 23:04:10] ALERT: Unauthorized admin access attempt"
    },
    {
        "timestamp": "2026-05-10 23:04:12.747706",
        "action": "Blocked malicious IP",
        "ip": "192.168.1.43",
        "threat": "[2026-05-10 23:04:10] ALERT: Unauthorized admin access attempt"
    },
    {
        "timestamp": "2026-05-10 23:04:15.755787",
        "action": "Blocked malicious activity",
        "threat": "[2026-05-10 23:04:15] ALERT: Potential brute force attack detected"
    },
    {
        "timestamp": "2026-05-10 23:04:15.755787",
        "action": "Blocked malicious IP",
        "ip": "192.168.1.1",
        "threat": "[2026-05-10 23:04:15] ALERT: Potential brute force attack detected"
    },
    {
        "timestamp": "2026-05-10 22:49:55.764495",
        "action": "Blocked malicious IP",
        "ip": "192.168.1.190",
        "threat": "[2026-05-10 22:44:39] ALERT: Privilege escalation detected"
    },
    {
        "timestamp": "2026-05-10 22:49:55.764771",
        "action": "Blocked malicious IP",
        "ip": "192.168.1.219",
        "threat": "[2026-05-10 22:44:44] ALERT: Privilege escalation detected"
    },
    {
        "timestamp": "2026-05-10 22:49:55.765403",
        "action": "Blocked malicious IP",
        "ip": "192.168.1.39",
        "threat": "[2026-05-10 22:44:59] ALERT: Potential brute force attack detected"
    },
    {
        "timestamp": "2026-05-10 22:49:55.765753",
        "action": "Blocked malicious IP",
        "ip": "192.168.1.160",
        "threat": "[2026-05-10 22:45:09] ALERT: Privilege escalation detected"
    },
    {
        "timestamp": "2026-05-10 22:49:55.766253",
        "action": "Blocked malicious IP",
        "ip": "192.168.1.211",
        "threat": "[2026-05-10 22:45:24] ALERT: Potential brute force attack detected"
    },
    {
        "timestamp": "2026-05-10 22:49:55.768196",
        "action": "Blocked malicious IP",
        "ip": "192.168.1.67",
        "threat": "[2026-05-10 22:46:14] ALERT: Potential brute force attack detected"
    },
    {
        "timestamp": "2026-05-10 22:49:55.768375",
        "action": "Blocked malicious IP",
        "ip": "192.168.1.238",
        "threat": "[2026-05-10 22:46:19] ALERT: Potential brute force attack detected"
    },
    {
        "timestamp": "2026-05-10 22:49:55.769217",
        "action": "Blocked malicious IP",
        "ip": "192.168.1.188",
        "threat": "[2026-05-10 22:46:39] ALERT: Unauthorized admin access attempt"
    },
    {
        "timestamp": "2026-05-10 22:49:55.769534",
        "action": "Blocked malicious IP",
        "ip": "192.168.1.173",
        "threat": "[2026-05-10 22:46:44] ALERT: Privilege escalation detected"
    },
    {
        "timestamp": "2026-05-10 22:49:55.772086",
        "action": "Blocked malicious IP",
        "ip": "192.168.1.176",
        "threat": "[2026-05-10 22:47:24] ALERT: Potential brute force attack detected"
    },
    {
        "timestamp": "2026-05-10 22:49:55.772494",
        "action": "Blocked malicious IP",
        "ip": "192.168.1.76",
        "threat": "[2026-05-10 22:47:29] ALERT: Privilege escalation detected"
    },
    {
        "timestamp": "2026-05-10 22:49:55.773240",
        "action": "Blocked malicious IP",
        "ip": "192.168.1.14",
        "threat": "[2026-05-10 22:47:39] ALERT: Potential brute force attack detected"
    },
    {
        "timestamp": "2026-05-10 22:49:55.774226",
        "action": "Blocked malicious IP",
        "ip": "192.168.1.12",
        "threat": "[2026-05-10 22:47:44] ALERT: Privilege escalation detected"
    },
    {
        "timestamp": "2026-05-10 22:49:55.774733",
        "action": "Blocked malicious IP",
        "ip": "192.168.1.39",
        "threat": "[2026-05-10 22:47:49] ALERT: Potential brute force attack detected"
    },
    {
        "timestamp": "2026-05-10 22:53:20.026158",
        "action": "Blocked malicious IP",
        "ip": "192.168.1.11",
        "threat": "[2026-05-10 22:53:19] ALERT: Potential brute force attack detected"
    },
    {
        "timestamp": "2026-05-10 22:53:23.499732",
        "action": "Blocked malicious IP",
        "ip": "192.168.1.35",
        "threat": "[2026-05-10 22:44:39] ALERT: Privilege escalation detected"
    },
    {
        "timestamp": "2026-05-10 22:53:23.500536",
        "action": "Blocked malicious IP",
        "ip": "192.168.1.239",
        "threat": "[2026-05-10 22:44:44] ALERT: Privilege escalation detected"
    },
    {
        "timestamp": "2026-05-10 22:53:23.502444",
        "action": "Blocked malicious IP",
        "ip": "192.168.1.178",
        "threat": "[2026-05-10 22:44:59] ALERT: Potential brute force attack detected"
    },
    {
        "timestamp": "2026-05-10 22:53:23.503978",
        "action": "Blocked malicious IP",
        "ip": "192.168.1.11",
        "threat": "[2026-05-10 22:45:09] ALERT: Privilege escalation detected"
    },
    {
        "timestamp": "2026-05-10 22:53:23.505447",
        "action": "Blocked malicious IP",
        "ip": "192.168.1.237",
        "threat": "[2026-05-10 22:45:24] ALERT: Potential brute force attack detected"
    },
    {
        "timestamp": "2026-05-10 22:53:23.510734",
        "action": "Blocked malicious IP",
        "ip": "192.168.1.96",
        "threat": "[2026-05-10 22:46:14] ALERT: Potential brute force attack detected"
    },
    {
        "timestamp": "2026-05-10 22:53:23.511153",
        "action": "Blocked malicious IP",
        "ip": "192.168.1.164",
        "threat": "[2026-05-10 22:46:19] ALERT: Potential brute force attack detected"
    },
    {
        "timestamp": "2026-05-10 22:53:23.513543",
        "action": "Blocked malicious IP",
        "ip": "192.168.1.79",
        "threat": "[2026-05-10 22:46:39] ALERT: Unauthorized admin access attempt"
    },
    {
        "timestamp": "2026-05-10 22:53:23.513899",
        "action": "Blocked malicious IP",
        "ip": "192.168.1.40",
        "threat": "[2026-05-10 22:46:44] ALERT: Privilege escalation detected"
    },
    {
        "timestamp": "2026-05-10 22:53:23.517331",
        "action": "Blocked malicious IP",
        "ip": "192.168.1.184",
        "threat": "[2026-05-10 22:47:24] ALERT: Potential brute force attack detected"
    },
    {
        "timestamp": "2026-05-10 22:53:23.517687",
        "action": "Blocked malicious IP",
        "ip": "192.168.1.206",
        "threat": "[2026-05-10 22:47:29] ALERT: Privilege escalation detected"
    },
    {
        "timestamp": "2026-05-10 22:53:23.520360",
        "action": "Blocked malicious IP",
        "ip": "192.168.1.12",
        "threat": "[2026-05-10 22:47:39] ALERT: Potential brute force attack detected"
    },
    {
        "timestamp": "2026-05-10 22:53:23.521745",
        "action": "Blocked malicious IP",
        "ip": "192.168.1.163",
        "threat": "[2026-05-10 22:47:44] ALERT: Privilege escalation detected"
    },
    {
        "timestamp": "2026-05-10 22:53:23.522923",
        "action": "Blocked malicious IP",
        "ip": "192.168.1.41",
        "threat": "[2026-05-10 22:47:49] ALERT: Potential brute force attack detected"
    },
    {
        "timestamp": "2026-05-10 22:53:23.526887",
        "action": "Blocked malicious IP",
        "ip": "192.168.1.106",
        "threat": "[2026-05-10 22:53:19] ALERT: Potential brute force attack detected"
    },
    {
        "timestamp": "2026-05-10 22:53:32.539637",
        "action": "Blocked malicious IP",
        "ip": "192.168.1.114",
        "threat": "[2026-05-10 22:53:29] ALERT: Potential brute force attack detected"
    },
    {
        "timestamp": "2026-05-10 22:53:35.546969",
        "action": "Blocked malicious IP",
        "ip": "192.168.1.122",
        "threat": "[2026-05-10 22:53:34] ALERT: Privilege escalation detected"
    },
    {
        "timestamp": "2026-05-10 22:53:50.576315",
        "action": "Blocked malicious IP",
        "ip": "192.168.1.142",
        "threat": "[2026-05-10 22:53:50] ALERT: Privilege escalation detected"
    },
    {
        "timestamp": "2026-05-10 22:54:02.594258",
        "action": "Blocked malicious IP",
        "ip": "192.168.1.205",
        "threat": "[2026-05-10 22:54:00] ALERT: Privilege escalation detected"
    },
    {
        "timestamp": "2026-05-10 22:54:05.596121",
        "action": "Blocked malicious IP",
        "ip": "192.168.1.191",
        "threat": "[2026-05-10 22:54:05] ALERT: Privilege escalation detected"
    },
    {
        "timestamp": "2026-05-10 22:54:11.603140",
        "action": "Blocked malicious IP",
        "ip": "192.168.1.85",
        "threat": "[2026-05-10 22:54:10] ALERT: Potential brute force attack detected"
    },
    {
        "timestamp": "2026-05-10 22:54:50.671974",
        "action": "Blocked malicious IP",
        "ip": "192.168.1.140",
        "threat": "[2026-05-10 22:54:50] ALERT: Unauthorized admin access attempt"
    },
    {
        "timestamp": "2026-05-10 22:54:56.686074",
        "action": "Blocked malicious IP",
        "ip": "192.168.1.68",
        "threat": "[2026-05-10 22:54:55] ALERT: Potential brute force attack detected"
    },
    {
        "timestamp": "2026-05-10 22:55:02.697815",
        "action": "Blocked malicious IP",
        "ip": "192.168.1.255",
        "threat": "[2026-05-10 22:55:00] ALERT: Privilege escalation detected"
    },
    {
        "timestamp": "2026-05-10 22:55:11.717179",
        "action": "Blocked malicious IP",
        "ip": "192.168.1.95",
        "threat": "[2026-05-10 22:55:10] ALERT: Potential brute force attack detected"
    },
    {
        "timestamp": "2026-05-10 22:55:17.728811",
        "action": "Blocked malicious IP",
        "ip": "192.168.1.143",
        "threat": "[2026-05-10 22:55:15] ALERT: Potential brute force attack detected"
    },
    {
        "timestamp": "2026-05-10 22:55:20.735930",
        "action": "Blocked malicious IP",
        "ip": "192.168.1.90",
        "threat": "[2026-05-10 22:55:20] ALERT: Privilege escalation detected"
    },
    {
        "timestamp": "2026-05-10 22:55:50.788402",
        "action": "Blocked malicious IP",
        "ip": "192.168.1.53",
        "threat": "[2026-05-10 22:55:50] ALERT: Unauthorized admin access attempt"
    },
    {
        "timestamp": "2026-05-10 22:55:56.798504",
        "action": "Blocked malicious IP",
        "ip": "192.168.1.81",
        "threat": "[2026-05-10 22:55:55] ALERT: Privilege escalation detected"
    },
    {
        "timestamp": "2026-05-10 22:56:11.821383",
        "action": "Blocked malicious IP",
        "ip": "192.168.1.105",
        "threat": "[2026-05-10 22:56:10] ALERT: Unauthorized admin access attempt"
    },
    {
        "timestamp": "2026-05-10 22:56:17.829278",
        "action": "Blocked malicious IP",
        "ip": "192.168.1.161",
        "threat": "[2026-05-10 22:56:15] ALERT: Privilege escalation detected"
    },
    {
        "timestamp": "2026-05-10 22:56:20.836480",
        "action": "Blocked malicious IP",
        "ip": "192.168.1.225",
        "threat": "[2026-05-10 22:56:20] ALERT: Unauthorized admin access attempt"
    },
    {
        "timestamp": "2026-05-10 22:56:32.858147",
        "action": "Blocked malicious IP",
        "ip": "192.168.1.75",
        "threat": "[2026-05-10 22:56:30] ALERT: Privilege escalation detected"
    },
    {
        "timestamp": "2026-05-10 22:56:56.894943",
        "action": "Blocked malicious IP",
        "ip": "192.168.1.249",
        "threat": "[2026-05-10 22:56:55] ALERT: Privilege escalation detected"
    },
    {
        "timestamp": "2026-05-10 22:57:02.902710",
        "action": "Blocked malicious IP",
        "ip": "192.168.1.18",
        "threat": "[2026-05-10 22:57:00] ALERT: Privilege escalation detected"
    },
    {
        "timestamp": "2026-05-10 22:57:17.924983",
        "action": "Blocked malicious IP",
        "ip": "192.168.1.83",
        "threat": "[2026-05-10 22:57:15] ALERT: Privilege escalation detected"
    },
    {
        "timestamp": "2026-05-10 22:57:26.941275",
        "action": "Blocked malicious IP",
        "ip": "192.168.1.131",
        "threat": "[2026-05-10 22:57:25] ALERT: Potential brute force attack detected"
    },
    {
        "timestamp": "2026-05-10 22:57:32.951860",
        "action": "Blocked malicious IP",
        "ip": "192.168.1.104",
        "threat": "[2026-05-10 22:57:30] ALERT: Privilege escalation detected"
    },
    {
        "timestamp": "2026-05-10 22:57:41.969677",
        "action": "Blocked malicious IP",
        "ip": "192.168.1.194",
        "threat": "[2026-05-10 22:57:40] ALERT: Unauthorized admin access attempt"
    },
    {
        "timestamp": "2026-05-10 22:57:47.981990",
        "action": "Blocked malicious IP",
        "ip": "192.168.1.242",
        "threat": "[2026-05-10 22:57:45] ALERT: Potential brute force attack detected"
    },
    {
        "timestamp": "2026-05-10 22:57:56.996588",
        "action": "Blocked malicious IP",
        "ip": "192.168.1.137",
        "threat": "[2026-05-10 22:57:55] ALERT: Unauthorized admin access attempt"
    },
    {
        "timestamp": "2026-05-10 22:58:03.002836",
        "action": "Blocked malicious IP",
        "ip": "192.168.1.168",
        "threat": "[2026-05-10 22:58:00] ALERT: Unauthorized admin access attempt"
    },
    {
        "timestamp": "2026-05-10 22:58:12.013620",
        "action": "Blocked malicious IP",
        "ip": "192.168.1.180",
        "threat": "[2026-05-10 22:58:10] ALERT: Unauthorized admin access attempt"
    },
    {
        "timestamp": "2026-05-10 22:58:21.031743",
        "action": "Blocked malicious IP",
        "ip": "192.168.1.169",
        "threat": "[2026-05-10 22:58:20] ALERT: Potential brute force attack detected"
    },
    {
        "timestamp": "2026-05-10 22:58:27.042272",
        "action": "Blocked malicious IP",
        "ip": "192.168.1.43",
        "threat": "[2026-05-10 22:58:25] ALERT: Potential brute force attack detected"
    },
    {
        "timestamp": "2026-05-10 22:58:33.051192",
        "action": "Blocked malicious IP",
        "ip": "192.168.1.197",
        "threat": "[2026-05-10 22:58:30] ALERT: Potential brute force attack detected"
    },
    {
        "timestamp": "2026-05-10 22:58:36.059919",
        "action": "Blocked malicious IP",
        "ip": "192.168.1.89",
        "threat": "[2026-05-10 22:58:35] ALERT: Unauthorized admin access attempt"
    },
    {
        "timestamp": "2026-05-10 22:58:57.105437",
        "action": "Blocked malicious IP",
        "ip": "192.168.1.165",
        "threat": "[2026-05-10 22:58:55] ALERT: Unauthorized admin access attempt"
    },
    {
        "timestamp": "2026-05-10 22:59:12.141499",
        "action": "Blocked malicious IP",
        "ip": "192.168.1.132",
        "threat": "[2026-05-10 22:59:10] ALERT: Potential brute force attack detected"
    },
    {
        "timestamp": "2026-05-10 22:59:21.155271",
        "action": "Blocked malicious IP",
        "ip": "192.168.1.87",
        "threat": "[2026-05-10 22:59:20] ALERT: Potential brute force attack detected"
    },
    {
        "timestamp": "2026-05-10 22:59:36.182294",
        "action": "Blocked malicious IP",
        "ip": "192.168.1.39",
        "threat": "[2026-05-10 22:59:35] ALERT: Potential brute force attack detected"
    },
    {
        "timestamp": "2026-05-10 22:59:57.225823",
        "action": "Blocked malicious IP",
        "ip": "192.168.1.42",
        "threat": "[2026-05-10 22:59:55] ALERT: Privilege escalation detected"
    },
    {
        "timestamp": "2026-05-10 23:00:18.258921",
        "action": "Blocked malicious IP",
        "ip": "192.168.1.137",
        "threat": "[2026-05-10 23:00:15] ALERT: Privilege escalation detected"
    },
    {
        "timestamp": "2026-05-10 23:00:21.268202",
        "action": "Blocked malicious IP",
        "ip": "192.168.1.3",
        "threat": "[2026-05-10 23:00:20] ALERT: Potential brute force attack detected"
    },
    {
        "timestamp": "2026-05-10 23:00:42.324661",
        "action": "Blocked malicious IP",
        "ip": "192.168.1.25",
        "threat": "[2026-05-10 23:00:40] ALERT: Potential brute force attack detected"
    },
    {
        "timestamp": "2026-05-10 23:01:06.409381",
        "action": "Blocked malicious IP",
        "ip": "192.168.1.115",
        "threat": "[2026-05-10 23:01:05] ALERT: Potential brute force attack detected"
    },
    {
        "timestamp": "2026-05-10 23:01:15.430150",
        "action": "Blocked malicious IP",
        "ip": "192.168.1.106",
        "threat": "[2026-05-10 23:01:15] ALERT: Privilege escalation detected"
    },
    {
        "timestamp": "2026-05-10 23:01:30.449118",
        "action": "Blocked malicious IP",
        "ip": "192.168.1.19",
        "threat": "[2026-05-10 23:01:30] ALERT: Privilege escalation detected"
    },
    {
        "timestamp": "2026-05-10 23:01:45.479250",
        "action": "Blocked malicious IP",
        "ip": "192.168.1.232",
        "threat": "[2026-05-10 23:01:45] ALERT: Privilege escalation detected"
    },
    {
        "timestamp": "2026-05-10 23:01:51.484329",
        "action": "Blocked malicious IP",
        "ip": "192.168.1.108",
        "threat": "[2026-05-10 23:01:50] ALERT: Potential brute force attack detected"
    },
    {
        "timestamp": "2026-05-10 23:01:57.496708",
        "action": "Blocked malicious IP",
        "ip": "192.168.1.226",
        "threat": "[2026-05-10 23:01:55] ALERT: Potential brute force attack detected"
    },
    {
        "timestamp": "2026-05-10 23:02:00.501230",
        "action": "Blocked malicious IP",
        "ip": "192.168.1.157",
        "threat": "[2026-05-10 23:02:00] ALERT: Potential brute force attack detected"
    },
    {
        "timestamp": "2026-05-10 23:02:15.533358",
        "action": "Blocked malicious IP",
        "ip": "192.168.1.66",
        "threat": "[2026-05-10 23:02:15] ALERT: Privilege escalation detected"
    },
    {
        "timestamp": "2026-05-10 23:02:36.568381",
        "action": "Blocked malicious IP",
        "ip": "192.168.1.50",
        "threat": "[2026-05-10 23:02:35] ALERT: Privilege escalation detected"
    },
    {
        "timestamp": "2026-05-10 23:02:45.581468",
        "action": "Blocked malicious IP",
        "ip": "192.168.1.19",
        "threat": "[2026-05-10 23:02:45] ALERT: Privilege escalation detected"
    },
    {
        "timestamp": "2026-05-10 23:03:06.619613",
        "action": "Blocked malicious IP",
        "ip": "192.168.1.79",
        "threat": "[2026-05-10 23:03:05] ALERT: Potential brute force attack detected"
    },
    {
        "timestamp": "2026-05-10 23:03:15.642316",
        "action": "Blocked malicious IP",
        "ip": "192.168.1.253",
        "threat": "[2026-05-10 23:03:15] ALERT: Unauthorized admin access attempt"
    },
    {
        "timestamp": "2026-05-10 23:03:27.663660",
        "action": "Blocked malicious IP",
        "ip": "192.168.1.86",
        "threat": "[2026-05-10 23:03:25] ALERT: Unauthorized admin access attempt"
    },
    {
        "timestamp": "2026-05-10 23:04:00.729616",
        "action": "Blocked malicious IP",
        "ip": "192.168.1.217",
        "threat": "[2026-05-10 23:04:00] ALERT: Privilege escalation detected"
    },
    {
        "timestamp": "2026-05-10 23:04:12.747706",
        "action": "Blocked malicious IP",
        "ip": "192.168.1.175",
        "threat": "[2026-05-10 23:04:10] ALERT: Unauthorized admin access attempt"
    },
    {
        "timestamp": "2026-05-10 23:04:15.755787",
        "action": "Blocked malicious IP",
        "ip": "192.168.1.155",
        "threat": "[2026-05-10 23:04:15] ALERT: Potential brute force attack detected"
    },
    {
        "timestamp": "2026-05-10 23:04:21.766526",
        "action": "Blocked malicious activity",
        "threat": "[2026-05-10 23:04:20] ALERT: Potential brute force attack detected"
    },
    {
        "timestamp": "2026-05-10 23:04:21.766526",
        "action": "Blocked malicious IP",
        "ip": "192.168.1.126",
        "threat": "[2026-05-10 23:04:20] ALERT: Potential brute force attack detected"
    },
    {
        "timestamp": "2026-05-10 23:04:36.803910",
        "action": "Blocked malicious activity",
        "threat": "[2026-05-10 23:04:35] ALERT: Potential brute force attack detected"
    },
    {
        "timestamp": "2026-05-10 23:04:36.803910",
        "action": "Blocked malicious IP",
        "ip": "192.168.1.72",
        "threat": "[2026-05-10 23:04:35] ALERT: Potential brute force attack detected"
    },
    {
        "timestamp": "2026-05-10 23:04:45.820070",
        "action": "Blocked malicious activity",
        "threat": "[2026-05-10 23:04:45] ALERT: Privilege escalation detected"
    },
    {
        "timestamp": "2026-05-10 23:04:45.820070",
        "action": "Blocked malicious IP",
        "ip": "192.168.1.228",
        "threat": "[2026-05-10 23:04:45] ALERT: Privilege escalation detected"
    },
    {
        "timestamp": "2026-05-10 23:04:51.832383",
        "action": "Blocked malicious activity",
        "threat": "[2026-05-10 23:04:50] ALERT: Unauthorized admin access attempt"
    },
    {
        "timestamp": "2026-05-10 23:04:51.832383",
        "action": "Blocked malicious IP",
        "ip": "192.168.1.102",
        "threat": "[2026-05-10 23:04:50] ALERT: Unauthorized admin access attempt"
    },
    {
        "timestamp": "2026-05-10 23:05:00.853586",
        "action": "Blocked malicious activity",
        "threat": "[2026-05-10 23:05:00] ALERT: Unauthorized admin access attempt"
    },
    {
        "timestamp": "2026-05-10 23:05:00.853586",
        "action": "Blocked malicious IP",
        "ip": "192.168.1.224",
        "threat": "[2026-05-10 23:05:00] ALERT: Unauthorized admin access attempt"
    },
    {
        "timestamp": "2026-05-10 23:05:12.879600",
        "action": "Blocked malicious activity",
        "threat": "[2026-05-10 23:05:10] ALERT: Potential brute force attack detected"
    },
    {
        "timestamp": "2026-05-10 23:05:12.879600",
        "action": "Blocked malicious IP",
        "ip": "192.168.1.49",
        "threat": "[2026-05-10 23:05:10] ALERT: Potential brute force attack detected"
    },
    {
        "timestamp": "2026-05-10 23:05:15.884349",
        "action": "Blocked malicious activity",
        "threat": "[2026-05-10 23:05:15] ALERT: Potential brute force attack detected"
    },
    {
        "timestamp": "2026-05-10 23:05:15.884349",
        "action": "Blocked malicious IP",
        "ip": "192.168.1.250",
        "threat": "[2026-05-10 23:05:15] ALERT: Potential brute force attack detected"
    },
    {
        "timestamp": "2026-05-10 23:05:27.905626",
        "action": "Blocked malicious activity",
        "threat": "[2026-05-10 23:05:25] ALERT: Unauthorized admin access attempt"
    },
    {
        "timestamp": "2026-05-10 23:05:27.905626",
        "action": "Blocked malicious IP",
        "ip": "192.168.1.225",
        "threat": "[2026-05-10 23:05:25] ALERT: Unauthorized admin access attempt"
    },
    {
        "timestamp": "2026-05-10 23:06:06.975646",
        "action": "Blocked malicious activity",
        "threat": "[2026-05-10 23:06:05] ALERT: Unauthorized admin access attempt"
    },
    {
        "timestamp": "2026-05-10 23:06:06.975646",
        "action": "Blocked malicious IP",
        "ip": "192.168.1.41",
        "threat": "[2026-05-10 23:06:05] ALERT: Unauthorized admin access attempt"
    },
    {
        "timestamp": "2026-05-10 23:06:12.986356",
        "action": "Blocked malicious activity",
        "threat": "[2026-05-10 23:06:10] ALERT: Potential brute force attack detected"
    },
    {
        "timestamp": "2026-05-10 23:06:12.986356",
        "action": "Blocked malicious IP",
        "ip": "192.168.1.26",
        "threat": "[2026-05-10 23:06:10] ALERT: Potential brute force attack detected"
    },
    {
        "timestamp": "2026-05-10 23:06:31.018075",
        "action": "Blocked malicious activity",
        "threat": "[2026-05-10 23:06:30] ALERT: Potential brute force attack detected"
    },
    {
        "timestamp": "2026-05-10 23:06:31.018075",
        "action": "Blocked malicious IP",
        "ip": "192.168.1.203",
        "threat": "[2026-05-10 23:06:30] ALERT: Potential brute force attack detected"
    }
]